{"namespace":"popup_anim","chat_setting_anim":{"anim_type":"size","easing":"linear","duration":0.25,"from":["80%","40%"],"to":["80%","80%"]},"start_anim":{"anim_type":"offset","easing":"linear","duration":0,"from":["-300%","-300%"],"to":["-310%","-310%"],"next":"@popup_anim.up_anim"},"up_anim":{"anim_type":"size","easing":"linear","duration":0,"from":[0,0],"to":[0,0],"next":"@popup_anim.wait_anim"},"wait_anim":{"anim_type":"wait","easing":"linear","duration":0.01,"next":"@popup_anim.down_anim"},"down_anim":{"anim_type":"offset","easing":"linear","duration":0.02,"from":[0,0],"to":[0,0],"next":"@popup_anim.end_anim"},"end_anim":{"anim_type":"size","easing":"out_cubic","duration":0.2,"from":["48%",20],"to":["48%",125]}}