{"namespace":"play_control","root_control@type.panel":{"size":["100%","100%"],"controls":[{"bg@crafting.bg":{"alpha":0.35,"color":[0.15,0.15,0.15],"layer":2,"texture":"Arok/textures/background/night"}},{"button_panel@play.button_panel_content_panel":{"anchor_from":"bottom_middle","anchor_to":"bottom_middle","size":["100%","12%"]}},{"root_panel@type.sp":{"size":["100%","100%"],"controls":[{"top_bar@type.panel":{"size":["100%","9.5%"],"controls":[{"bg@type.image":{"alpha":0.75,"fill":true,"layer":2,"texture":"Arok/textures/background/white"}},{"back_button_default@type.image":{"texture":"Arok/textures/icon/back_button","color":"black","anchor_from":"left_middle","anchor_to":"left_middle","layer":5,"offset":[12,0],"size":[10,12]}},{"label@type.label":{"anchor_from":"left_middle","anchor_to":"left_middle","text":"world.management","layer":5,"offset":[25,0],"color":"black"}},{"return_to_game_button@pause.pause_button_template":{"size":["15%","100%"],"anchor_from":"left_middle","anchor_to":"left_middle","$pressed_button_name":"button.menu_exit","layer":7,"$default_button_texture":"textures/ui/background","$hover_button_texture":"textures/ui/background","$pressed_button_texture":"textures/ui/background"}},{"editor_settings_menu_button@common_buttons.light_content_button":{"layer":9,"offset":["-2%",0],"size":[21,21],"anchor_from":"top_right","anchor_to":"top_right","$pressed_button_name":"button.editor_settings","$button_content":"play.editor_settings_image_content","focus_identifier":"close_button","focus_change_left":"FOCUS_OVERRIDE_STOP","focus_change_up":"FOCUS_OVERRIDE_STOP","focus_change_right":"FOCUS_OVERRIDE_STOP"}}]}},{"line@crafting.bg":{"size":["100%","0.12%"],"alpha":0.95,"layer":500,"texture":"Arok/textures/background/white"}},{"content@type.hp":{"size":["100%","90.3%"],"controls":[{"help_root_panel@common.scrolling_panel":{"size":["15%","100%"],"anchor_from":"center","anchor_to":"center","$scrolling_content":"play_control.tab_panel","$show_background":false,"$scroll_size":["0.1px","100%"],"$scrolling_panel_size":["100%","100%"],"$scroll_box_mouse_image_control":"","$always_handle_scrolling":true}},{"content_panel@type.panel":{"size":["85%","100%"],"controls":[{"tab1@play_control.tab_panel_1":{"size":["100%","100%"]}},{"tab2@play_control.tab_panel_2":{"size":["100%","100%"]}},{"tab3@play_control.tab_panel_3":{"size":["100%","100%"]}}]}}]}}]}}]},"tab_panel@type.sp":{"size":["100%","100%"],"controls":[{"nothing@type.panel":{"size":["100%","5%"]}},{"1@play.world_navigation_tab":{"size":["100%","22%"]}},{"2@play.friends_navigation_tab":{"size":["100%","22%"]}},{"3@play.server_navigation_tab":{"size":["100%","22%"]}}]},"tab_panel_1@type.hp":{"controls":[{"worlds_tab_content@play.worlds_tab_content_panel":{"size":["95%","100%"]}},{"0@type.panel":{"size":["5%","100%"]}}]},"tab_panel_2@type.panel":{"controls":[{"friends_tab_content@play.friends_tab_content_panel":{"size":["100%","100%"]}}]},"tab_panel_3@type.panel":{"controls":[{"server_tab_content_panel@play.server_tab_content_panel":{"size":["100%","100%"]}}]}}