{"namespace":"play_anim","play_come_size":{"anim_type":"size","easing":"in_cubic","duration":3,"from":["104%","104%"],"to":["115%","115%"],"next":"@play_anim.play_offset_left"},"play_offset_left":{"anim_type":"offset","easing":"linear","duration":1.7,"from":[0,0],"to":["7%",0],"next":"@play_anim.play_offset_right"},"play_offset_right":{"anim_type":"offset","easing":"linear","duration":2.5,"from":["7%",0],"to":["-5%","-2%"],"next":"@play_anim.play_offset_middle"},"play_offset_middle":{"anim_type":"offset","easing":"linear","duration":1.8,"from":["-5%","-2%"],"to":["1%","2%"],"next":"@play_anim.play_back_size"},"play_back_size":{"anim_type":"size","easing":"linear","duration":4,"from":["115%","115%"],"to":["104%","104%"],"next":"@play_anim.play_wait"},"play_wait":{"anim_type":"wait","easing":"linear","duration":0.25,"next":"@play_anim.play_ready"},"play_ready":{"anim_type":"offset","easing":"linear","duration":1.2,"from":["1%","2%"],"to":[0,0],"next":"@play_anim.play_come_size"},"play_come_pop":{"anim_type":"size","easing":"out_cubic","duration":0.65,"from":["100%","155%"],"to":["100%","100%"],"play_event":"screen.entrance_pop","end_event":"screen.entrance_end"},"play_come_push":{"anim_type":"size","easing":"out_cubic","duration":0.65,"from":["100%","155%"],"to":["100%","100%"],"play_event":"screen.entrance_push","reset_event":"screen.entrance_end"},"play_exit_push":{"anim_type":"size","easing":"out_cubic","duration":0.8,"to":["145%","100%"],"from":["100%","100%"],"play_event":"screen.exit_push","end_event":"screen.exit_end"},"play_exit_pop":{"anim_type":"size","easing":"out_cubic","duration":0.8,"to":["145%","100%"],"from":["100%","100%"],"play_event":"screen.exit_pop","end_event":"screen.exit_end"},"play_function_come_pop":{"anim_type":"offset","easing":"in_expo","duration":0.25,"from":["0%","35%"],"to":["0%","0%"],"play_event":"screen.entrance_pop","end_event":"screen.entrance_end"},"play_function_come_push":{"anim_type":"offset","easing":"out_expo","duration":0.25,"from":["0%","35%"],"to":["0%","0%"],"play_event":"screen.entrance_push","reset_event":"screen.entrance_end"}}